docs/.gitignore
docs/conf.py
docs/index.md
docs/justfile
docs/requirements.txt
docs/integration_examples/create_ingredient.md
docs/integration_examples/create_output.md
docs/integration_examples/index.md
docs/integration_examples/upload_file.md
docs/static/logo_blue.png
docs/static/favicons/android-chrome-192x192.png
docs/static/favicons/android-chrome-512x512.png
docs/static/favicons/apple-touch-icon.png
docs/static/favicons/browserconfig.xml
docs/static/favicons/favicon-16x16.png
docs/static/favicons/favicon-32x32.png
docs/static/favicons/manifest.json
docs/static/favicons/mstile-150x150.png
docs/static/favicons/safari-pinned-tab.svg
examples/async_batch.py
examples/basic_auth.py
examples/create_entity.py
examples/create_ingredient_sdk.py
examples/download_files.py
examples/edit_recipe_inputs.py
examples/invoke_uploader.py
examples/oauth.py
examples/set_recipe_metadata_file.py
examples/set_recipe_output_file_sdk.py
examples/upload_files.py
examples/integration-server/pyproject.toml
examples/integration-server/jobs/materials_auto/concurrent_cron.py
examples/integration-server/jobs/materials_auto/example_cron.py
examples/integration-server/jobs/materials_auto/example_http.py
examples/integration-server/jobs/materials_auto/example_instrument.py
examples/integration-server/jobs/materials_auto/example_parse.py
examples/integration-server/jobs/materials_auto/example_predictions.py
examples/integration-server/jobs/materials_auto/example_runsheet_wh.py
examples/integration-server/jobs/materials_auto/example_wh.py
examples/integration-server/jobs/materials_auto/profile.yaml
pkgs/__init__.py
pkgs/py.typed
pkgs/argument_parser/__init__.py
pkgs/argument_parser/_is_enum.py
pkgs/argument_parser/_is_namedtuple.py
pkgs/argument_parser/argument_parser.py
pkgs/argument_parser/case_convert.py
pkgs/filesystem_utils/__init__.py
pkgs/filesystem_utils/_blob_session.py
pkgs/filesystem_utils/_gdrive_session.py
pkgs/filesystem_utils/_local_session.py
pkgs/filesystem_utils/_s3_session.py
uncountablepythonsdk-0.0.147.dist-info/METADATA
uncountablepythonsdk-0.0.147.dist-info/WHEEL
uncountablepythonsdk-0.0.147.dist-info/top_level.txt
uncountablepythonsdk-0.0.147.dist-info/RECORD
