Metadata-Version: 2.4
Name: UncountablePythonSDK
Version: 0.0.147
Summary: Uncountable SDK
Project-URL: Homepage, https://github.com/uncountableinc/uncountable-python-sdk
Project-URL: Repository, https://github.com/uncountableinc/uncountable-python-sdk.git
Project-URL: Issues, https://github.com/uncountableinc/uncountable-python-sdk/issues
Keywords: uncountable,sdk,api,uncountable-sdk
Classifier: Development Status :: 4 - Beta
Classifier: Environment :: Console
Classifier: Intended Audience :: Developers
Classifier: Operating System :: OS Independent
Classifier: Programming Language :: Python :: 3
Classifier: Topic :: Software Development
Classifier: Topic :: Utilities
Classifier: Typing :: Typed
Requires-Python: >=3.11
Requires-Dist: aiotus==1.*
Requires-Dist: aiohttp==3.*
Requires-Dist: requests==2.*
Requires-Dist: SQLAlchemy>=1.4.0
Requires-Dist: APScheduler==3.*
Requires-Dist: python-dateutil==2.*
Requires-Dist: shelljob==0.*
Requires-Dist: PyYAML==6.*
Requires-Dist: google-api-python-client==2.*
Requires-Dist: tqdm==4.*
Requires-Dist: pysftp==0.*
Requires-Dist: opentelemetry-api==1.*
Requires-Dist: opentelemetry-exporter-otlp-proto-common==1.*
Requires-Dist: opentelemetry-exporter-otlp-proto-http==1.*
Requires-Dist: opentelemetry-sdk<1.39.0
Requires-Dist: paramiko==3.*
Requires-Dist: boto3==1.*
Requires-Dist: flask==3.*
Requires-Dist: simplejson==3.*
Requires-Dist: grpcio==1.67.1
Requires-Dist: protobuf>=4.21.1
Requires-Dist: azure-storage-blob==12.*
Requires-Dist: boto3-stubs[essential,ses]==1.*
Requires-Dist: msgspec<0.21,>=0.19
Requires-Dist: tabulate==0.9.0
Requires-Dist: types-psutil~=7.1.3
Requires-Dist: psutil>=5.9.0
Provides-Extra: test
Requires-Dist: mypy==1.*; extra == "test"
Requires-Dist: ruff==0.*; extra == "test"
Requires-Dist: pytest>=8; extra == "test"
Requires-Dist: coverage[toml]==7.*; extra == "test"
Requires-Dist: pytest-cov==7.*; extra == "test"
Requires-Dist: pytest-xdist==3.*; extra == "test"
